{
  "build": {
    "core": "stm32",
    "cpu": "cortex-m4",
    "extra_flags": "-DSTM32F334x8 -DSTM32F3",
    "f_cpu": "72000000L",
    "mcu": "STM32F334K6Tx",
    "product_line": "STM32F334x8",
    "variant": "STM32F3xx/F303K(6-8)T_F334K(4-6-8)T"
  },
  "debug": {
    "jlink_device": "stm32f334k6",
    "openocd_target": "stm32f3x",
    "svd_path": "STM32F3x4.svd"
  },
  "frameworks": [
    "arduino",
    "cmsis",
    "stm32cube",
    "libopencm3"
  ],
  "name": "STM32F334K6Tx (16k RAM 32k Flash)",
  "upload": {
    "maximum_ram_size": 16384,
    "maximum_size": 32768,
    "protocol": "serial",
    "protocols": [
      "blackmagic",
      "dfu",
      "serial",
      "stlink",
      "jlink",
      "cmsis-dap"
    ]
  },
  "url": "https://www.st.com/en/microcontrollers-microprocessors/stm32f334k6.html",
  "vendor": "ST"
}