{
  "build": {
    "core": "stm32",
    "cpu": "cortex-m4",
    "extra_flags": "-DSTM32F303xE -DSTM32F3",
    "f_cpu": "72000000L",
    "mcu": "STM32F303RETx",
    "product_line": "STM32F303xE",
    "variant": "STM32F3xx/F303R(D-E)T"
  },
  "debug": {
    "jlink_device": "stm32f303re",
    "openocd_target": "stm32f3x",
    "svd_path": "STM32F303.svd"
  },
  "frameworks": [
    "arduino",
    "cmsis",
    "stm32cube",
    "libopencm3"
  ],
  "name": "STM32F303RETx (80k RAM 512k Flash)",
  "upload": {
    "maximum_ram_size": 81920,
    "maximum_size": 524288,
    "protocol": "serial",
    "protocols": [
      "blackmagic",
      "dfu",
      "serial",
      "stlink",
      "jlink",
      "cmsis-dap"
    ]
  },
  "url": "https://www.st.com/en/microcontrollers-microprocessors/stm32f303re.html",
  "vendor": "ST"
}